[
    {
        "ID": "10441414",
        "To": "Shafwan",
        "From": "Fahim",
        "Date": "16-08-2023",
        "Amount": "500",
        "Signature": "Fahim",
        "Approved Votes": 1
    },
    {
        "ID": "37543806",
        "To": "Fahim",
        "From": "Shafwan",
        "Date": "16-08-2023",
        "Amount": "500",
        "Signature": "Shafwan",
        "Approved Votes": 2
    },
    {
        "ID": "67581099",
        "To": "Fahim",
        "From": "Shafwan",
        "Date": "16-08-2023",
        "Amount": "1000",
        "Signature": "Shafwan",
        "Approved Votes": 1
    }
]